lifelogger/__init__.py
lifelogger/__main__.py
lifelogger/cli.py
lifelogger/config.py
lifelogger/models.py
lifelogger/permissions.py
lifelogger/capture/__init__.py
lifelogger/capture/keyboard.py
lifelogger/capture/mouse.py
lifelogger/capture/screenshot.py
lifelogger/daemon/__init__.py
lifelogger/daemon/runner.py
lifelogger/storage/__init__.py
lifelogger/storage/jsonl.py
lifelogger/summarize/__init__.py
lifelogger/summarize/llm.py
lifelogger/summarize/processor.py
lifelogger_daemon-0.2.1.dist-info/licenses/LICENSE
tests/__init__.py
tests/test_config.py
tests/test_models.py
lifelogger_daemon-0.2.1.dist-info/METADATA
lifelogger_daemon-0.2.1.dist-info/WHEEL
lifelogger_daemon-0.2.1.dist-info/entry_points.txt
lifelogger_daemon-0.2.1.dist-info/top_level.txt
lifelogger_daemon-0.2.1.dist-info/RECORD
