Metadata-Version: 2.4
Name: lifelogger-daemon
Version: 0.2.1
Summary: Personal activity tracking daemon with LLM summarization
Author: Jacob
License: MIT
Project-URL: Homepage, https://github.com/JacobFV/lifelogger
Project-URL: Repository, https://github.com/JacobFV/lifelogger
Project-URL: Issues, https://github.com/JacobFV/lifelogger/issues
Keywords: activity-tracking,productivity,llm,automation
Classifier: Development Status :: 3 - Alpha
Classifier: Environment :: Console
Classifier: Intended Audience :: Developers
Classifier: Intended Audience :: End Users/Desktop
Classifier: License :: OSI Approved :: MIT License
Classifier: Operating System :: OS Independent
Classifier: Programming Language :: Python :: 3
Classifier: Programming Language :: Python :: 3.10
Classifier: Programming Language :: Python :: 3.11
Classifier: Programming Language :: Python :: 3.12
Classifier: Topic :: System :: Monitoring
Requires-Python: >=3.10
License-File: LICENSE
Requires-Dist: pydantic>=2.0
Requires-Dist: pynput>=1.7.6
Requires-Dist: mss>=9.0.0
Requires-Dist: pillow>=10.0.0
Requires-Dist: croniter>=2.0.0
Requires-Dist: openai>=1.0.0
Requires-Dist: click>=8.0.0
Requires-Dist: pydantic-settings>=2.0.0
Provides-Extra: dev
Requires-Dist: pytest>=7.0.0; extra == "dev"
Requires-Dist: pytest-cov>=4.0.0; extra == "dev"
Requires-Dist: mypy>=1.0.0; extra == "dev"
Requires-Dist: ruff>=0.1.0; extra == "dev"
Dynamic: license-file
